enviPath_python/__init__.py
enviPath_python/__version__.py
enviPath_python/enums.py
enviPath_python/enviPath.py
enviPath_python/objects.py
enviPath_python/utils.py
enviPath_python-0.2.3.dist-info/LICENSE
enviPath_python-0.2.3.dist-info/METADATA
enviPath_python-0.2.3.dist-info/WHEEL
enviPath_python-0.2.3.dist-info/top_level.txt
enviPath_python-0.2.3.dist-info/RECORD
