Metadata-Version: 2.1
Name: enviPath-python
Version: 0.2.3
Summary: A python client to interact with enviPath
Author-email: Tim Lorsbach <lorsbach@envipath.com>, Jasmin Hafner <jasmin.hafner@eawag.ch>, Albert Anguera Sempere <albert.anguerasempere@uzh.ch>
Project-URL: Homepage, https://github.com/enviPath/enviPath-python
Project-URL: Bug Tracker, https://github.com/enviPath/enviPath-python/issues
Classifier: Programming Language :: Python :: 3
Classifier: License :: OSI Approved :: MIT License
Classifier: Operating System :: OS Independent
Requires-Python: >=3.7
License-File: LICENSE
Requires-Dist: requests
